cite_seq_count/__init__.py
cite_seq_count/__main__.py
cite_seq_count/io.py
cite_seq_count/preprocessing.py
cite_seq_count/processing.py
cite_seq_count/secondsToText.py
CITE_seq_Count-1.4.5.dist-info/LICENSE.txt
CITE_seq_Count-1.4.5.dist-info/METADATA
CITE_seq_Count-1.4.5.dist-info/WHEEL
CITE_seq_Count-1.4.5.dist-info/entry_points.txt
CITE_seq_Count-1.4.5.dist-info/top_level.txt
CITE_seq_Count-1.4.5.dist-info/RECORD
