Metadata-Version: 2.1
Name: CITE-seq-Count
Version: 1.4.5
Summary: A python package to map reads from CITE-seq or hashing data for single cell experiments
Home-page: https://github.com/Hoohm/CITE-seq-Count/
Author: Roelli Patrick
Author-email: patrick.roelli@gmail.com
License: UNKNOWN
Platform: UNKNOWN
Classifier: Programming Language :: Python :: 3
Classifier: License :: OSI Approved :: MIT License
Classifier: Operating System :: OS Independent
Requires-Python: >=3.6
Requires-Dist: python-levenshtein (>=0.12.0)
Requires-Dist: scipy (>=1.1.0)
Requires-Dist: multiprocess (>=0.70.6.1)
Requires-Dist: umi-tools (==1.0.0)
Requires-Dist: pytest (==4.1.0)
Requires-Dist: pytest-dependency (==0.4.0)
Requires-Dist: pandas (>=0.23.4)
Requires-Dist: pybktree (==1.1)
